BETA/desacoplamiento.py
BETA/raster_format_translation.py
BETA/rectangularization.py
BETA/text_prompts.py
BETA/tile_movements.py
apb_spatial_computer_vision/__init__.py
apb_spatial_computer_vision/fire_run.py
apb_spatial_computer_vision/lang_sam_utilities.py
apb_spatial_computer_vision/main.py
apb_spatial_computer_vision/raster_utilities.py
apb_spatial_computer_vision/sam_utilities.py
apb_spatial_computer_vision/vector_utilities.py
apb_spatial_computer_vision-1.1.0.dist-info/licenses/LICENSE
docs/automate_index_md.py
docs/automate_yaml.py
scripts/NDVI.py
scripts/__init__.py
scripts/field_work.py
scripts/filter_noise.py
scripts/geometricSimplification.py
scripts/image_reuniting_splitting.py
scripts/segmentation.py
scripts/self_intersection.py
scripts/vegetation_indices.py
test/test_DINO.py
test/test_SAM.py
test/test_pyramid.py
apb_spatial_computer_vision-1.1.0.dist-info/METADATA
apb_spatial_computer_vision-1.1.0.dist-info/WHEEL
apb_spatial_computer_vision-1.1.0.dist-info/top_level.txt
apb_spatial_computer_vision-1.1.0.dist-info/RECORD
