Metadata-Version: 2.4
Name: apb_spatial_computer_vision
Version: 1.1.0
Summary: Python package to integrate image pyramids and raster/vector algorithms for computer vision at Port of Barcelona. Allows text, bounding box and point-based segmentation based on SAMGeo and GroundingDINO. Please refer to the homepage https://victorpachecoaznar.github.io/TFG/
Author-email: Víctor Pacheco Aznar <vpachecoaznar@gmail.com>
License: MIT License
Requires-Python: >=3.7
License-File: LICENSE
Provides-Extra: cpu
Requires-Dist: gdal==3.10.2; extra == "cpu"
Requires-Dist: geopandas==1.0.1; extra == "cpu"
Requires-Dist: numpy==2.2.3; extra == "cpu"
Requires-Dist: pandas==2.2.3; extra == "cpu"
Requires-Dist: shapely==2.0.7; extra == "cpu"
Requires-Dist: segment-geospatial==0.12.4; extra == "cpu"
Requires-Dist: duckdb==1.2.0; extra == "cpu"
Requires-Dist: matplotlib==3.10.0; extra == "cpu"
Requires-Dist: pyproj==3.7.1; extra == "cpu"
Requires-Dist: scipy==1.15.2; extra == "cpu"
Requires-Dist: pyarrow==20.0.0; extra == "cpu"
Requires-Dist: openpyxl==3.1.5; extra == "cpu"
Provides-Extra: cuda
Requires-Dist: gdal==3.10.2; extra == "cuda"
Requires-Dist: geopandas==1.0.1; extra == "cuda"
Requires-Dist: numpy==2.2.3; extra == "cuda"
Requires-Dist: pandas==2.2.3; extra == "cuda"
Requires-Dist: shapely==2.0.7; extra == "cuda"
Requires-Dist: segment-geospatial==0.12.4; extra == "cuda"
Requires-Dist: duckdb==1.2.0; extra == "cuda"
Requires-Dist: matplotlib==3.10.0; extra == "cuda"
Requires-Dist: pyproj==3.7.1; extra == "cuda"
Requires-Dist: scipy==1.15.2; extra == "cuda"
Requires-Dist: torch==2.5.1+cu118; extra == "cuda"
Requires-Dist: pyarrow==20.0.0; extra == "cuda"
Requires-Dist: openpyxl==3.1.5; extra == "cuda"
Dynamic: license-file
